[{"node": "None_ctrl8", "objectColorR": 0.0, "useObjectColor": 0, "overrideEnabled": false, "overrideLevelOfDetail": 0, "objectColorB": 0.0, "aimMatrix": null, "overrideColorB": 0.0, "objectColorG": 0.0, "overrideColorG": 0.0, "size": [0.8, 0.8, 1.0000000000000009], "overridePlayback": true, "outlinerColorR": 0.0, "ghostColorPreA": 1.0, "overrideDisplayType": 0, "outlinerColorG": 0.0, "overrideColor": 0, "outlinerColorB": 0.0, "wireColorB": 0.0, "overrideColorR": 0.0, "wireColorG": 0.0, "overrideVisibility": true, "ghostColorPostG": 0.6779999732971191, "ghostColorPreB": 1.0, "ghostColorPostB": 0.6629999876022339, "ghostColorPreG": 1.0, "wireColorR": 0.0, "layerOverrideColor": 0, "ghostColorPostA": 1.0, "ghostColorPreR": 0.44699999690055847, "ghostColorPostR": 0.878000020980835, "name": "arrow_ik_fk", "overrideRGBColors": false, "overrideShading": true, "overrideTexturing": true, "objectColor": 0, "useOutlinerColor": false}, {"intermediateObject": false, "useObjectColor": 0, "aiMinPixelWidth": 0.0, "overrideEnabled": false, "antialiasingLevel": 1, "ignoreSelfShadowing": false, "ghostPostSteps": 3, "aiVisibleInSpecularTransmission": true, "primaryVisibility": true, "wireColorB": 0.0, "aiVisibleInDiffuseReflection": true, "wireColorG": 0.0, "ghostColorPostG": 0.6779999732971191, "motionBlur": true, "ghostColorPostB": 0.6629999876022339, "ghostColorPostA": 1.0, "wireColorR": 0.0, "ghostColorPostR": 0.878000020980835, "displayColors": false, "overrideShading": true, "receiveShadows": true, "overrideTexturing": true, "volumeSamples": 1, "shadingSamples": 1, "objectColor": 0, "aiRenderCurve": false, "asBackground": false, "boundingBoxMinX": -0.4, "boundingBoxMinY": -0.4, "boundingBoxMinZ": -0.49284247844877727, "depthJitter": false, "renderVolume": false, "aimMatrix": null, "templateVersion": 0, "ghosting": false, "outlinerColorR": 0.0, "identification": 0, "template": false, "outlinerColorG": 0.0, "outlinerColorB": 0.0, "geometryAntialiasingOverride": false, "aiVisibleInVolume": true, "nodeType": "nurbsCurve", "degree": 1, "aiExportRefPoints": true, "inPlace": false, "hiddenInOutliner": false, "overrideColor": 0, "aiMode": 0, "useOutlinerColor": false, "boundingBoxCenterZ": 0.007157521551223123, "aiMatte": false, "boundingBoxCenterY": 0.0, "aiCurveWidth": 0.009999999776482582, "aiVisibleInDiffuseTransmission": true, "dispGeometry": true, "lineWidth": -1.0, "selectionChildHighlighting": true, "aiVisibleInSpecularReflection": true, "tweak": false, "maxVisibilitySamples": 1, "spans": 14, "overrideLevelOfDetail": 0, "overridePlayback": true, "isHistoricallyInteresting": 2, "aiSelfShadows": true, "aiOpaque": true, "aiCurveShaderB": 0.0, "relativeTweak": true, "aiCurveShaderG": 0.0, "objectColorR": 0.0, "tweakSize": -1, "aiCurveShaderR": 0.0, "visibleInReflections": false, "hardwareFogMultiplier": 1.0, "form": 0, "boundingBoxCenterX": 0.0, "visibility": true, "layerOverrideColor": 0, "visibleInRefractions": false, "maxVisibilitySamplesOverride": false, "overrideRGBColors": false, "visibleFraction": 1.0, "frozen": false, "boundingBoxSizeX": 0.8, "boundingBoxSizeY": 0.8, "boundingBoxSizeZ": 1.0000000000000009, "ghostPreSteps": 3, "maxShadingSamples": 1, "overrideColorR": 0.0, "renderType": 0, "objectColorB": 0.0, "dispCurveEndPoints": false, "objectColorG": 0.0, "overrideColorG": 0.0, "shadingSamplesOverride": false, "isCollapsed": false, "overrideColorB": 0.0, "blackBox": false, "ghostingControl": 0, "aiSampleRate": 5, "castsShadows": true, "dispHull": false, "hideOnPlayback": false, "boundingBoxMaxZ": 0.5071575215512235, "overrideDisplayType": 0, "boundingBoxMaxX": 0.4, "boundingBoxMaxY": 0.4, "nodeState": 0, "overrideVisibility": true, "ghostColorPreA": 1.0, "ghostColorPreB": 1.0, "displayImmediate": false, "ghostColorPreG": 1.0, "dispEP": false, "layerRenderable": true, "volumeSamplesOverride": false, "lodVisibility": true, "ghostColorPreR": 0.44699999690055847, "uiTreatment": 0, "ghostStepSize": 1, "viewMode": 2, "points": [[0.0, -1.0918784085699965e-22, 0.5071575215512235], [-0.4, -1.0918784085699965e-22, 0.1071575215512224], [-0.2, -1.0918784085699965e-22, 0.1071575215512224], [-0.2, -1.0918784085699965e-22, -0.49284247844877727], [0.2, -1.0918784085699965e-22, -0.49284247844877727], [0.2, -1.0918784085699965e-22, 0.1071575215512224], [0.4, -1.0918784085699965e-22, 0.1071575215512224], [0.0, -1.0918784085699965e-22, 0.5071575215512235], [0.0, 0.4, 0.1071575215512224], [0.0, 0.2, 0.1071575215512224], [0.0, 0.2, -0.49284247844877727], [0.0, -0.2, -0.49284247844877727], [0.0, -0.2, 0.1071575215512224], [0.0, -0.4, 0.1071575215512224], [0.0, -1.0918784085699965e-22, 0.5071575215512235]], "caching": false, "dispCV": false}]